[
  {
    "id": 1,
    "name": "Productivity",
    "district": "Kampar",
    "ics": "ICS 1",
    "children": [
      {
        "id": 2,
        "name": "Training",
        "district": "Kampar",
        "ics": "ICS 1",
        "children": [
          {
            "id": 3,
            "name": "Financial Literacy",
            "district": "Kampar",
            "ics": "ICS 1",
            "evidence": "https://drive.google.com/drive/folders/xxxx"
          }
        ]
      }
    ]
  },
  {
    "id": 8,
    "name": "Sustainability",
    "district": "Rokan Hulu",
    "ics": "ICS 2",
    "children": [
      {
        "id": 9,
        "name": "Traceability",
        "district": "Rokan Hulu",
        "ics": "ICS 2",
        "evidence": "https://drive.google.com/file/d/abc"
      }
    ]
  }
]
